uncurlx/__init__.py
uncurlx/__main__.py
uncurlx/api.py
uncurlx/ast_api.py
uncurlx/py.typed
uncurlx-0.0.13b2.dist-info/entry_points.txt
uncurlx-0.0.13b2.dist-info/licenses/LICENSE
uncurlx-0.0.13b2.dist-info/WHEEL
uncurlx-0.0.13b2.dist-info/METADATA
uncurlx-0.0.13b2.dist-info/RECORD
