Metadata-Version: 2.4
Name: uncurlx
Version: 0.0.13b2
Summary: Uncurl-X is a library that allows you to convert curl requests into python code that uses [httpx](https://www.python-httpx.org/).
Keywords: curl,http,cli,command-line,uncurl,httpx,uncurlx
Author-email: whichoneiwonder <whichoneiwonder@github.com>
Requires-Python: >=3.9
License-Expression: Apache-2.0
Classifier: Development Status :: 4 - Beta
Classifier: Intended Audience :: Developers
Classifier: Natural Language :: English
Classifier: Programming Language :: Python :: 3.9
Classifier: Programming Language :: Python :: 3.10
Classifier: Programming Language :: Python :: 3.11
Classifier: Programming Language :: Python :: 3.12
Classifier: Programming Language :: Python :: 3.13
Classifier: Programming Language :: Python :: 3.14
Classifier: Topic :: Internet :: WWW/HTTP
Classifier: Topic :: Software Development :: Libraries :: Python Modules
Classifier: Topic :: Software Development :: Code Generators
Classifier: Topic :: Utilities
Classifier: Intended Audience :: Information Technology
Classifier: Intended Audience :: System Administrators
Classifier: Intended Audience :: Developers
Classifier: Environment :: Console
License-File: LICENSE
Requires-Dist: pyperclip >=1.9, <2 ; extra == "clip"
Project-URL: Home, https://github.com/whichoneiwonder/uncurl-x
Provides-Extra: clip
